syncv/__init__.py
syncv/cli.py
syncv/clipboard.py
syncv/core.py
syncv/keyboard_shortcuts.py
syncv/network.py
syncv/storage.py
syncv-0.1.1.dist-info/METADATA
syncv-0.1.1.dist-info/WHEEL
syncv-0.1.1.dist-info/entry_points.txt
syncv-0.1.1.dist-info/top_level.txt
syncv-0.1.1.dist-info/RECORD
